tests/test.bw
bin/bamread
bwread/read.py
bwread/__init__.py
bwread/src/bwread.c
bwread/src/bwread.pyx
bwread/src/bwread.cpython-311-i386-linux-musl.so
bwread/src/__init__.py
bwread-0.0.5.dist-info/top_level.txt
bwread-0.0.5.dist-info/RECORD
bwread-0.0.5.dist-info/METADATA
bwread-0.0.5.dist-info/WHEEL
