Metadata-Version: 2.1
Name: bwread
Version: 0.0.5
Summary: Read bigwig files into Python data science formats.
Author-email: Endre Bakken Stovner <endbak@pm.me>
License: MIT
Project-URL: Homepage, http://github.com/pyranges/bwread
Keywords: bigwig
Classifier: Programming Language :: Python :: 3
Classifier: Development Status :: 4 - Beta
Classifier: Environment :: Other Environment
Classifier: Intended Audience :: Developers
Classifier: Intended Audience :: Science/Research
Classifier: License :: OSI Approved :: MIT License
Classifier: Operating System :: POSIX :: Linux
Classifier: Operating System :: MacOS :: MacOS X
Classifier: Topic :: Scientific/Engineering
Requires-Dist: numpy
Requires-Dist: natsort
Requires-Dist: cython
Requires-Dist: pandas
Requires-Dist: pyBigWig
Requires-Dist: pyranges
Provides-Extra: dev
Requires-Dist: black ; extra == 'dev'
Requires-Dist: bumpver ; extra == 'dev'
Requires-Dist: isort ; extra == 'dev'
Requires-Dist: pip-tools ; extra == 'dev'
Requires-Dist: pytest ; extra == 'dev'
